CHANGES.rst
LICENSE
MANIFEST.in
README.rst
setup.py
Flask_Split.egg-info/PKG-INFO
Flask_Split.egg-info/SOURCES.txt
Flask_Split.egg-info/dependency_links.txt
Flask_Split.egg-info/not-zip-safe
Flask_Split.egg-info/pbr.json
Flask_Split.egg-info/requires.txt
Flask_Split.egg-info/top_level.txt
docs/Makefile
docs/conf.py
docs/index.rst
docs/make.bat
flask_split/__init__.py
flask_split/core.py
flask_split/models.py
flask_split/utils.py
flask_split/views.py
flask_split/static/css/bootstrap.css
flask_split/static/css/bootstrap.min.css
flask_split/static/css/dashboard.css
flask_split/static/js/bootstrap.js
flask_split/static/js/bootstrap.min.js
flask_split/static/js/dashboard.js
flask_split/templates/split/_experiment.html
flask_split/templates/split/base.html
flask_split/templates/split/index.html
tests/__init__.py
tests/test_dashboard.py
tests/test_extension.py
tests/test_models.py