Metadata-Version: 1.1
Name: Flask-Split
Version: 0.4.0
Summary: A/B testing for your Flask application
Home-page: http://github.com/jpvanhal/flask-split
Author: Janne Vanhala
Author-email: janne.vanhala@gmail.com
License: MIT
Platform: any
Classifier: Development Status :: 4 - Beta
Classifier: Environment :: Web Environment
Classifier: Intended Audience :: Developers
Classifier: License :: OSI Approved :: BSD License
Classifier: Operating System :: OS Independent
Classifier: Programming Language :: Python
Classifier: Topic :: Internet :: WWW/HTTP :: Dynamic Content
Classifier: Topic :: Software Development :: Libraries :: Python Modules
